pyconnldap/__init__.py
pyconnldap/connection.py
pyconnldap/test.py
pyconnldap-1.0.2.dist-info/METADATA
pyconnldap-1.0.2.dist-info/WHEEL
pyconnldap-1.0.2.dist-info/top_level.txt
pyconnldap-1.0.2.dist-info/RECORD
