Metadata-Version: 2.4
Name: pyconnldap
Version: 1.0.2
Summary: A simplified Python library for LDAP connection and operations.
Author-email: Josephus <orca099210@gmail.com>
License-Expression: MIT
Keywords: ldap,domain system,connection
Requires-Python: >=3.10
Requires-Dist: ldap3
Requires-Dist: dotenv
